LICENSE
MANIFEST.in
README.md
setup.py
figurine/__init__.py
figurine/base.py
figurine.egg-info/PKG-INFO
figurine.egg-info/SOURCES.txt
figurine.egg-info/dependency_links.txt
figurine.egg-info/top_level.txt