Metadata-Version: 1.0
Name: figurine
Version: 0.1
Summary: Simple, structure only models with inheritance
Home-page: http://github.com/aventurella/figurine
Author: Adam Venturella
Author-email: aventurella@gmail.com
License: Copyright (c) 2012 Adam Venturella.
